<?xml version="1.0" encoding="UTF-8" ?>

<!--
Copyright (C) Herbert Wagner Nov2014-2016
see Read-Me.txt for all copyrights in the base folder of this aircraft
-->

<PropertyList>

 <path>stairs.ac</path>
 
 <animation>
	  <type>select</type>	  
	  <condition>
		  <property>sim/multiplay/generic/int[3]</property>		  
	  </condition>
  </animation>
  
  <animation>
  <type>scale</type>
  
  <property>sim/multiplay/generic/int[3]</property>
  <offset>1</offset>
  <x-max>1.65</x-max>
  <y-max>1.32</y-max>
  <z-max>2.19</z-max>
  <x-factor>1.65</x-factor>
  <y-factor>1.32</y-factor>
  <z-factor>2.19</z-factor>
 </animation>

</PropertyList>
